joblib-stubs/__init__.pyi
joblib-stubs/_cloudpickle_wrapper.pyi
joblib-stubs/_dask.pyi
joblib-stubs/_memmapping_reducer.pyi
joblib-stubs/_multiprocessing_helpers.pyi
joblib-stubs/_parallel_backends.pyi
joblib-stubs/_store_backends.pyi
joblib-stubs/_typeshed.pyi
joblib-stubs/_utils.pyi
joblib-stubs/backports.pyi
joblib-stubs/compressor.pyi
joblib-stubs/disk.pyi
joblib-stubs/executor.pyi
joblib-stubs/func_inspect.pyi
joblib-stubs/hashing.pyi
joblib-stubs/logger.pyi
joblib-stubs/memory.pyi
joblib-stubs/numpy_pickle.pyi
joblib-stubs/numpy_pickle_compat.pyi
joblib-stubs/numpy_pickle_utils.pyi
joblib-stubs/parallel.pyi
joblib-stubs/pool.pyi
joblib-stubs/py.typed
joblib_stubs-1.5.3.1.20260117.dist-info/METADATA
joblib_stubs-1.5.3.1.20260117.dist-info/WHEEL
joblib_stubs-1.5.3.1.20260117.dist-info/licenses/LICENSE
joblib_stubs-1.5.3.1.20260117.dist-info/RECORD
